provenance_rename_operator/__init__.py
provenance_rename_operator/provenance_rename_operator.py
amsterdam_airflow_provenance_rename_operator-1.1.dist-info/LICENSE.txt
amsterdam_airflow_provenance_rename_operator-1.1.dist-info/WHEEL
amsterdam_airflow_provenance_rename_operator-1.1.dist-info/METADATA
amsterdam_airflow_provenance_rename_operator-1.1.dist-info/RECORD
